lkapi/__init__.py
lkapi/client.py
lkapi/credential.py
lkapi/parser.py
lkapi-0.2.0.dist-info/WHEEL
lkapi-0.2.0.dist-info/METADATA
lkapi-0.2.0.dist-info/RECORD
