Metadata-Version: 2.3
Name: lkapi
Version: 0.2.0
Summary: Python client code to work with the Lightkeeper API
Requires-Dist: numpy>=2.2.3
Requires-Dist: pandas>=2.2.3
Requires-Dist: requests>=2.32.3
Requires-Python: >=3.10
